{
  "station": "KLAX",
  "date": "July 11, 2026",
  "scrapedAt": "5:41 PM \u00b7 WU",
  "ts": 1783791713350,
  "source": "WU live",
  "hourly": [
    {
      "time": "11:00 am",
      "temp": 73,
      "cloud": 43,
      "hum": 68,
      "wind": 8,
      "dir": "SW",
      "cond": "Partly Cloudy"
    },
    {
      "time": "12:00 pm",
      "temp": 74,
      "cloud": 80,
      "hum": 65,
      "wind": 10,
      "dir": "SW",
      "cond": "Mostly Cloudy"
    },
    {
      "time": "1:00 pm",
      "temp": 75,
      "cloud": 73,
      "hum": 64,
      "wind": 10,
      "dir": "SW",
      "cond": "Mostly Cloudy"
    },
    {
      "time": "2:00 pm",
      "temp": 75,
      "cloud": 76,
      "hum": 63,
      "wind": 9,
      "dir": "WSW",
      "cond": "Mostly Cloudy"
    },
    {
      "time": "3:00 pm",
      "temp": 75,
      "cloud": 83,
      "hum": 64,
      "wind": 10,
      "dir": "WSW",
      "cond": "Cloudy"
    },
    {
      "time": "4:00 pm",
      "temp": 73,
      "cloud": 89,
      "hum": 68,
      "wind": 10,
      "dir": "SW",
      "cond": "Cloudy"
    },
    {
      "time": "5:00 pm",
      "temp": 73,
      "cloud": 88,
      "hum": 68,
      "wind": 10,
      "dir": "WSW",
      "cond": "Cloudy"
    },
    {
      "time": "6:00 pm",
      "temp": 71,
      "cloud": 80,
      "hum": 72,
      "wind": 10,
      "dir": "WSW",
      "cond": "Mostly Cloudy"
    },
    {
      "time": "7:00 pm",
      "temp": 70,
      "cloud": 82,
      "hum": 75,
      "wind": 9,
      "dir": "W",
      "cond": "Cloudy"
    },
    {
      "time": "8:00 pm",
      "temp": 69,
      "cloud": 77,
      "hum": 79,
      "wind": 9,
      "dir": "W",
      "cond": "Mostly Cloudy"
    },
    {
      "time": "9:00 pm",
      "temp": 68,
      "cloud": 71,
      "hum": 81,
      "wind": 8,
      "dir": "WSW",
      "cond": "Mostly Cloudy"
    },
    {
      "time": "10:00 pm",
      "temp": 68,
      "cloud": 90,
      "hum": 82,
      "wind": 8,
      "dir": "WSW",
      "cond": "Cloudy"
    },
    {
      "time": "11:00 pm",
      "temp": 68,
      "cloud": 74,
      "hum": 83,
      "wind": 7,
      "dir": "WSW",
      "cond": "Mostly Cloudy"
    }
  ]
}